fastapp/__init__.py
fastapp/__main__.py
fastapp/_cli.py
fastapp/_utils.py
fastapp/_version.py
fastapp/serve.py
fastapp/app/__init__.py
fastapp/app/base.py
fastapp/app/example.py
fastapp/app/machine_learning.py
fastapp/app/utils.py
fastapp/app/static/fastapp.css
fastapp/app/templates/index.html
fastapp/config/__init__.py
fastapp/config/gunicorn_config.py
fastapp/config/logging_config.yaml
fastapp/config/nginx.conf
fastapp/config/swagger.json
fastapp/config/uvicorn_logging_config.yaml
fastapp/models/__init__.py
fastapp/models/base.py
fastapp/models/bodies.py
fastapp/models/responses.py
fastapp-0.1.7.dist-info/LICENSE
fastapp-0.1.7.dist-info/METADATA
fastapp-0.1.7.dist-info/WHEEL
fastapp-0.1.7.dist-info/entry_points.txt
fastapp-0.1.7.dist-info/top_level.txt
fastapp-0.1.7.dist-info/RECORD
