Metadata-Version: 2.1
Name: fastapp
Version: 0.1.7
Summary: Machine Learning ASGI Server with FastAPI
Home-page: https://github.com/juftin/fastapp
Author: Justin Flannery
Author-email: juftin@juftin.com
Maintainer: Justin Flannery
Maintainer-email: juftin@juftin.com
Project-URL: Discussions, https://github.com/juftin/fastapp/discussions
Project-URL: Bug Tracker, https://github.com/juftin/fastapp/issues
Project-URL: Documentation, https://juftin.com/fastapp
Classifier: License :: OSI Approved :: MIT License
Classifier: Operating System :: OS Independent
Classifier: Programming Language :: Python :: 3
Classifier: Programming Language :: Python :: 3.7
Classifier: Programming Language :: Python :: 3.8
Classifier: Programming Language :: Python :: 3.9
Classifier: Programming Language :: Python :: 3.10
Requires-Python: >=3.7
Provides-Extra: example
Provides-Extra: dev
License-File: LICENSE
